[
  {
    "path": "/",
    "resourceSizes": [
      { "resourceType": "document", "budget": 5 },
      { "resourceType": "script", "budget": 55 },
      { "resourceType": "stylesheet", "budget": 12 },
      { "resourceType": "image", "budget": 12 },
      { "resourceType": "font", "budget": 58 },
      { "resourceType": "total", "budget": 270 }
    ],
    "resourceCounts": [
      { "resourceType": "document", "budget": 1 },
      { "resourceType": "script", "budget": 11 },
      { "resourceType": "stylesheet", "budget": 2 },
      { "resourceType": "image", "budget": 2 },
      { "resourceType": "font", "budget": 3 },
      { "resourceType": "total", "budget": 20 }
    ]
  }
]
